locaspy/__init__.py
locaspy/ip_info.py
locaspy-1.0.4.dist-info/LICENSE
locaspy-1.0.4.dist-info/METADATA
locaspy-1.0.4.dist-info/WHEEL
locaspy-1.0.4.dist-info/top_level.txt
locaspy-1.0.4.dist-info/RECORD
