Metadata-Version: 2.1
Name: locaspy
Version: 1.0.4
Summary: A tool for fetching location, weather, and map link based on IP address.
Home-page: https://mrfidal.in/basic-pip-package/locaspy
Author: Fidal
Author-email: mrfidal@proton.me
Classifier: Programming Language :: Python :: 3
Classifier: License :: OSI Approved :: MIT License
Classifier: Operating System :: OS Independent
Requires-Python: >=3.6
License-File: LICENSE
Requires-Dist: requests
